[
    {
      "pictures": [],
      "event_pic": "https://wowslider.com/sliders/demo-93/data1/images/lake.jpg",
      "title": "yosi party",
      "date": "2019-01-16",
      "owner": "ohad",
      "location": "tel aviv",
      "description": "this is a description",
      "id": 1
    },
    {
        "pictures": [],
        "event_pic": "https://wowslider.com/sliders/demo-93/data1/images/lake.jpg",
        "title": "yosi party",
        "date": "2019-01-16",
        "owner": "ohad",
        "location": "tel aviv",
        "description": "this is a description",
        "id": 2
      },
      {
        "pictures": [],
        "event_pic": "https://wowslider.com/sliders/demo-93/data1/images/lake.jpg",
        "title": "yosi party",
        "date": "2019-01-16",
        "owner": "ohad",
        "location": "tel aviv",
        "description": "this is a description",
        "id": 3
      },
      {
        "pictures": [],
        "event_pic": "https://wowslider.com/sliders/demo-93/data1/images/lake.jpg",
        "title": "yosi party",
        "date": "2019-01-16",
        "owner": "ohad",
        "location": "tel aviv",
        "description": "this is a description",
        "id": 4
      },
      {
        "pictures": [],
        "event_pic": "https://wowslider.com/sliders/demo-93/data1/images/lake.jpg",
        "title": "yosi party",
        "date": "2019-01-16",
        "owner": "ohad",
        "location": "tel aviv",
        "description": "this is a description",
        "id": 5
      }
  ]